README
setup.py
test_page.egg-info/PKG-INFO
test_page.egg-info/SOURCES.txt
test_page.egg-info/dependency_links.txt
test_page.egg-info/top_level.txt
tidypage/__init__.py
tidypage/test.py