Metadata-Version: 1.0
Name: test-page
Version: 0.1
Summary: this just a test for python pypi .
Home-page: UNKNOWN
Author: wjolin
Author-email: 792994035@qq.com
License: MIT
Platform: any
